Auto_HookPoint/HookedTransformerAdapter.py
Auto_HookPoint/__init__.py
Auto_HookPoint/check.py
Auto_HookPoint/hook.py
Auto_HookPoint/utils.py
tests/__init__.py
tests/speed_benchmark.py
tests/test_adapter.py
tests/test_auto_hook.py
tests/test_check_auto_wrap.py
tests/test_models.py
tests/test_sae_lens_train.py
tests/test_utils.py
auto_hookpoint-0.6.0.dist-info/METADATA
auto_hookpoint-0.6.0.dist-info/WHEEL
auto_hookpoint-0.6.0.dist-info/RECORD
