Metadata-Version: 2.1
Name: Auto_HookPoint
Version: 0.6.0
Summary: Make any model compatible with transformer_lens
Home-page: https://github.com/HP2706/Auto_HookPoint
License: MIT
Author: HP
Author-email: hprjdk@gmail.com
Requires-Python: >=3.8
Classifier: License :: OSI Approved :: MIT License
Classifier: Programming Language :: Python :: 3
Classifier: Programming Language :: Python :: 3.8
Classifier: Programming Language :: Python :: 3.9
Classifier: Programming Language :: Python :: 3.10
Classifier: Programming Language :: Python :: 3.11
Classifier: Programming Language :: Python :: 3.12
Requires-Dist: transformer_lens (>=2.2.2,<3.0.0)
Project-URL: Repository, https://github.com/HP2706/Auto_HookPoint
